Metadata-Version: 2.1
Name: simple-metrics-manager
Version: 0.4.0
Summary: Just a simple system to manage a set of metrics (string name / function / returned data) that supports caching (memory and disk)
Home-page: http://pypi.python.org/pypi/simple_metrics_manager/
Author: David N. Mashburn
Author-email: david.n.mashburn@gmail.com
License: LICENSE.txt
Platform: UNKNOWN
